Lab1/blackbox.v
module blackbox(z, q, p, k);
    output z;
    input  q, p, k;
    wire   w00, w08, w09, w12, w17, w21, w26, w27, w33, w40, w43, w48, w58, w65, w69, w78, w82, w86, w90, w91, w93, w97;
    or  o62(z, w21, w43, w97);
    and a47(w21, w27, w91, w65);
    not n31(w65, w93);
    and a52(w43, w91, w93, w27);
    and a3(w97, w48, w17);
    not n55(w48, w91);
    or  o95(w17, w69, w90);
    and a30(w69, w27, w93);
    and a23(w90, w00, w27);
    not n49(w00, w93);
    or  o53(w91, k, w12, p);
    not n71(w12, q);
    or  o11(w93, w78, w08);
    and a77(w78, w33, w82);
    not n20(w33, p);
    not n5(w82, k);
    and a51(w08, p, w09, q);
    not n16(w09, k);
    and a94(w27, w40, w86);
    not n25(w40, k);
    or  o96(w86, p, w58);
    and a41(w58, q, w26);
    not n72(w26, p);
endmodule // blackbox

Lab1/blackbox_tb.v
module blackbox_test;
    reg q, p, k;
    wire out;

    blackbox box(out, q, p, k);

    initial begin
        $dumpfile("blackbox.vcd");
        $dumpvars(0, blackbox_test);

        q = 0; p = 0; k = 0; #10;
        q = 0; p = 0; k = 1; #10;
        q = 0; p = 1; k = 0; #10;
        q = 0; p = 1; k = 1; #10;
        q = 1; p = 0; k = 0; #10;
        q = 1; p = 0; k = 1; #10;
        q = 1; p = 1; k = 0; #10;
        q = 1; p = 1; k = 1; #10;

        $finish;
    end

    initial
        $monitor("At time %2t, q = %d p = %d k = %d out = %d",
            $time, q, p, k, out);

endmodule // blackbox_test

Lab1/blackbox.vcd
$date
	Thu Jan 28 16:04:06 2021
$end
$version
	Icarus Verilog
$end
$timescale
	1s
$end
$scope module blackbox_test $end
$var wire 1 ! out $end
$var reg 1 " k $end
$var reg 1 # p $end
$var reg 1 $ q $end
$scope module box $end
$var wire 1 " k $end
$var wire 1 # p $end
$var wire 1 $ q $end
$var wire 1 % w00 $end
$var wire 1 & w08 $end
$var wire 1 ' w09 $end
$var wire 1 ( w12 $end
$var wire 1 ) w17 $end
$var wire 1 * w21 $end
$var wire 1 + w26 $end
$var wire 1 , w27 $end
$var wire 1 - w33 $end
$var wire 1 . w40 $end
$var wire 1 / w43 $end
$var wire 1 0 w48 $end
$var wire 1 1 w58 $end
$var wire 1 2 w65 $end
$var wire 1 3 w69 $end
$var wire 1 4 w78 $end
$var wire 1 5 w82 $end
$var wire 1 6 w86 $end
$var wire 1 7 w90 $end
$var wire 1 8 w91 $end
$var wire 1 9 w93 $end
$var wire 1 : w97 $end
$var wire 1 ! z $end
$upscope $end
$upscope $end
$enddefinitions $end
#0
$dumpvars
0:
19
18
07
06
15
14
03
02
01
00
0/
1.
1-
0,
1+
0*
0)
1(
1'
0&
0%
0$
0#
0"
0!
$end
#10
1%
12
09
04
05
0'
0.
1"
#20
1)
1!
17
1*
1,
15
1'
1.
0-
16
0+
0"
1#
#30
0)
0!
07
0*
0,
05
0'
0.
1"
#40
1!
1:
1)
0%
13
02
1,
19
10
14
11
15
1'
1.
08
1-
16
1+
0(
0"
0#
1$
#50
0!
1%
12
0)
0:
09
03
00
04
0,
18
05
0'
0.
1"
#60
0%
13
1/
02
1)
1!
19
07
0*
1&
1,
01
15
1'
1.
0-
0+
0"
1#
#70
1%
12
0)
0!
09
03
0/
0&
0,
05
0'
0.
1"
